getjobfromsitevn/GetJob.py
getjobfromsitevn/__init__.py
getjobfromsitevn-pkg/GetJob.py
getjobfromsitevn-pkg/__init__.py
GetJobFromSiteVN-0.0.2.dist-info/METADATA
GetJobFromSiteVN-0.0.2.dist-info/WHEEL
GetJobFromSiteVN-0.0.2.dist-info/top_level.txt
GetJobFromSiteVN-0.0.2.dist-info/RECORD
